news_mining_db/__init__.py
news_mining_db/alembic.ini
news_mining_db/alembic/env.py
news_mining_db/commands/__init__.py
news_mining_db/migrations/20553112b75f_tag_reltion_add_news_vector_add.py
news_mining_db/migrations/46885c39f167_site_add.py
news_mining_db/migrations/564923304d28_user_model_add.py
news_mining_db/migrations/62e733cd17d3_news_model_add_site_update.py
news_mining_db/migrations/b1a7e861b22c_news_model_add.py
news_mining_db/migrations/b70458a3a914_quote_allowed_add_to_news.py
news_mining_db/migrations/c7f0898e5393_tag_model_add.py
news_mining_db/migrations/fe6cf974587e_site_model_updated.py
news_mining_db/models/__init__.py
news_mining_db/models/base_model.py
news_mining_db/models/news.py
news_mining_db/models/news_tag.py
news_mining_db/models/site.py
news_mining_db/models/tag.py
news_mining_db/models/user.py
news_mining_db-0.6.5.dist-info/LICENSE
news_mining_db-0.6.5.dist-info/METADATA
news_mining_db-0.6.5.dist-info/WHEEL
news_mining_db-0.6.5.dist-info/entry_points.txt
news_mining_db-0.6.5.dist-info/top_level.txt
news_mining_db-0.6.5.dist-info/RECORD
