Metadata-Version: 2.1
Name: news-mining-db
Version: 0.6.5
Summary: Sheared db models for news-mining project
Home-page: https://github.com/Myroslav341/news-mining-db
Author: Myroslav Havryliuk
Author-email: myroslav04@gmail.com
License: MIT
Platform: UNKNOWN
Requires-Dist: sqlalchemy
Requires-Dist: alembic
Requires-Dist: psycopg2
